dishka/__init__.py
dishka/async_container.py
dishka/container.py
dishka/container_objects.py
dishka/context_proxy.py
dishka/exception_base.py
dishka/exceptions.py
dishka/factory_compiler.py
dishka/py.typed
dishka/registry.py
dishka/registry_builder.py
dishka/_adaptix/common.py
dishka/_adaptix/feature_requirement.py
dishka/_adaptix/type_tools/__init__.py
dishka/_adaptix/type_tools/basic_utils.py
dishka/_adaptix/type_tools/constants.py
dishka/_adaptix/type_tools/fundamentals.py
dishka/_adaptix/type_tools/generic_resolver.py
dishka/_adaptix/type_tools/implicit_params.py
dishka/_adaptix/type_tools/norm_utils.py
dishka/_adaptix/type_tools/normalize_type.py
dishka/_adaptix/type_tools/type_evaler.py
dishka/dependency_source/__init__.py
dishka/dependency_source/alias.py
dishka/dependency_source/composite.py
dishka/dependency_source/context_var.py
dishka/dependency_source/decorator.py
dishka/dependency_source/factory.py
dishka/dependency_source/type_match.py
dishka/entities/__init__.py
dishka/entities/component.py
dishka/entities/depends_marker.py
dishka/entities/factory_type.py
dishka/entities/key.py
dishka/entities/provides_marker.py
dishka/entities/scope.py
dishka/entities/type_alias_type.py
dishka/entities/validation_settigs.py
dishka/entities/validation_settings.py
dishka/entities/with_parents.py
dishka/integrations/__init__.py
dishka/integrations/aiogram.py
dishka/integrations/aiogram_dialog.py
dishka/integrations/aiohttp.py
dishka/integrations/arq.py
dishka/integrations/base.py
dishka/integrations/celery.py
dishka/integrations/click.py
dishka/integrations/exceptions.py
dishka/integrations/fastapi.py
dishka/integrations/flask.py
dishka/integrations/grpcio.py
dishka/integrations/litestar.py
dishka/integrations/sanic.py
dishka/integrations/starlette.py
dishka/integrations/taskiq.py
dishka/integrations/telebot.py
dishka/integrations/faststream/__init__.py
dishka/integrations/faststream/faststream_05.py
dishka/integrations/faststream/faststream_06.py
dishka-1.7.1.dist-info/licenses/LICENSE
dishka-1.7.1.dist-info/METADATA
dishka-1.7.1.dist-info/WHEEL
dishka-1.7.1.dist-info/top_level.txt
dishka-1.7.1.dist-info/RECORD
