Metadata-Version: 2.4
Name: dishka
Version: 1.7.1
Summary: Cute DI framework with scopes and agreeable API
Author-email: Andrey Tikhonov <17@itishka.org>
License: Apache-2.0
Project-URL: Source, https://github.com/reagento/dishka
Project-URL: Homepage, https://github.com/reagento/dishka
Project-URL: Documentation, https://dishka.readthedocs.io/en/stable/
Project-URL: Bug Tracker, https://github.com/reagento/dishka/issues
Classifier: Programming Language :: Python :: 3.10
Classifier: Programming Language :: Python :: 3.11
Classifier: Programming Language :: Python :: 3.12
Classifier: Programming Language :: Python :: 3.13
Classifier: Programming Language :: Python :: 3.14
Classifier: Topic :: Software Development :: Libraries
Classifier: Typing :: Typed
Classifier: Intended Audience :: Developers
Classifier: License :: OSI Approved :: Apache Software License
Classifier: Operating System :: OS Independent
Requires-Python: >=3.10
License-File: LICENSE
Requires-Dist: exceptiongroup>=1.1.3; python_version < "3.11"
Dynamic: license-file
